fraiseql-1.9.1.dist-info/METADATA
fraiseql-1.9.1.dist-info/WHEEL
fraiseql-1.9.1.dist-info/entry_points.txt
fraiseql-1.9.1.dist-info/licenses/LICENSE
fraiseql.libs/libcrypto-c19c2cf8.so.3
fraiseql.libs/libssl-63597a81.so.3
fraiseql/__init__.py
fraiseql/__init__.pyi
fraiseql/__version__.py
fraiseql/_fraiseql_rs.cpython-313-x86_64-linux-gnu.so
fraiseql/analysis/__init__.py
fraiseql/analysis/complexity_config.py
fraiseql/analysis/query_analyzer.py
fraiseql/analysis/query_complexity.py
fraiseql/audit/__init__.py
fraiseql/audit/security_logger.py
fraiseql/auth/__init__.py
fraiseql/auth/auth0.py
fraiseql/auth/auth0_with_revocation.py
fraiseql/auth/base.py
fraiseql/auth/decorators.py
fraiseql/auth/native/__init__.py
fraiseql/auth/native/factory.py
fraiseql/auth/native/middleware.py
fraiseql/auth/native/models.py
fraiseql/auth/native/provider.py
fraiseql/auth/native/router.py
fraiseql/auth/native/tokens.py
fraiseql/auth/rust_provider.py
fraiseql/auth/token_revocation.py
fraiseql/cache/__init__.py
fraiseql/cache/view_metadata.py
fraiseql/caching/__init__.py
fraiseql/caching/cache_key.py
fraiseql/caching/postgres_cache.py
fraiseql/caching/repository_integration.py
fraiseql/caching/result_cache.py
fraiseql/caching/schema_analyzer.py
fraiseql/cli/__init__.py
fraiseql/cli/commands/__init__.py
fraiseql/cli/commands/check.py
fraiseql/cli/commands/dev.py
fraiseql/cli/commands/doctor.py
fraiseql/cli/commands/generate.py
fraiseql/cli/commands/init.py
fraiseql/cli/commands/migrate.py
fraiseql/cli/commands/sbom.py
fraiseql/cli/commands/sql.py
fraiseql/cli/commands/turbo.py
fraiseql/cli/main.py
fraiseql/cli/sql_helper.py
fraiseql/config/__init__.py
fraiseql/config/schema_config.py
fraiseql/core/__init__.py
fraiseql/core/ast_parser.py
fraiseql/core/database.py
fraiseql/core/exceptions.py
fraiseql/core/fragment_resolver.py
fraiseql/core/graphql_parser.py
fraiseql/core/graphql_pipeline.py
fraiseql/core/graphql_type.py
fraiseql/core/nested_field_resolver.py
fraiseql/core/query_builder.py
fraiseql/core/registry.py
fraiseql/core/rust_pipeline.py
fraiseql/core/rust_transformer.py
fraiseql/core/schema_serializer.py
fraiseql-1.9.1.dist-info/RECORD
