Metadata-Version: 2.4
Name: fraiseql
Version: 1.9.1
Classifier: Development Status :: 5 - Production/Stable
Classifier: Intended Audience :: Developers
Classifier: Topic :: Software Development :: Libraries :: Python Modules
Classifier: License :: OSI Approved :: MIT License
Classifier: Programming Language :: Python :: 3
Classifier: Programming Language :: Python :: 3.13
Classifier: Framework :: FastAPI
Classifier: Topic :: Database
Classifier: Topic :: Internet :: WWW/HTTP :: HTTP Servers
Classifier: Topic :: Software Development :: Libraries :: Application Frameworks
Classifier: Typing :: Typed
Classifier: Operating System :: OS Independent
Requires-Dist: fastapi>=0.115.12
Requires-Dist: starlette>=0.49.1
Requires-Dist: graphql-core>=3.2.0
Requires-Dist: psycopg[pool]>=3.2.6
Requires-Dist: psycopg-pool>=3.2.6
Requires-Dist: uvicorn>=0.34.3
Requires-Dist: pydantic>=2.0.0
Requires-Dist: pydantic-settings>=2.0.0
Requires-Dist: httpx>=0.25.0
Requires-Dist: pyjwt[crypto]>=2.8.0
Requires-Dist: python-dateutil>=2.8.0
Requires-Dist: click>=8.1.0
Requires-Dist: python-dotenv>=1.0.0
Requires-Dist: structlog>=23.0.0
Requires-Dist: passlib[argon2]>=1.7.4
Requires-Dist: aiosqlite>=0.21.0
Requires-Dist: typer>=0.12.0
Requires-Dist: rich>=13.7.0
Requires-Dist: pyyaml>=6.0.1
Requires-Dist: sqlparse>=0.5.0
Requires-Dist: fraiseql-confiture>=0.1.0
Requires-Dist: jinja2>=3.1.0
Requires-Dist: urllib3>=2.6.0
Requires-Dist: black>=25.0.1 ; extra == 'dev'
Requires-Dist: pre-commit>=4.2.0 ; extra == 'dev'
Requires-Dist: pytest>=8.3.5 ; extra == 'dev'
Requires-Dist: pytest-asyncio>=1.0.0 ; extra == 'dev'
Requires-Dist: pytest-timeout>=2.4.0 ; extra == 'dev'
Requires-Dist: faker>=37.5.3 ; extra == 'dev'
Requires-Dist: testcontainers[postgres]>=4.10.0 ; extra == 'dev'
Requires-Dist: testcontainers[vault]>=4.10.0 ; extra == 'dev'
Requires-Dist: docker>=7.1.0 ; extra == 'dev'
Requires-Dist: pytest-xdist>=3.5.0 ; extra == 'dev'
Requires-Dist: pytest-watch>=1.0.0 ; extra == 'dev'
Requires-Dist: pytest-cov>=4.0.0 ; extra == 'dev'
Requires-Dist: pytest-mock>=3.11.0 ; extra == 'dev'
Requires-Dist: pytest-benchmark>=4.0.0 ; extra == 'dev'
Requires-Dist: tox>=4.0.0 ; extra == 'dev'
Requires-Dist: ruff>=0.13.0 ; extra == 'dev'
Requires-Dist: build>=1.0.0 ; extra == 'dev'
Requires-Dist: twine>=6.1.0 ; extra == 'dev'
Requires-Dist: pyyaml>=6.0.0 ; extra == 'dev'
Requires-Dist: prometheus-client>=0.20.0 ; extra == 'dev'
Requires-Dist: email-validator>=2.0.0 ; extra == 'dev'
Requires-Dist: hvac>=2.0.0 ; extra == 'dev'
Requires-Dist: moto[kms]>=5.0.0 ; extra == 'dev'
Requires-Dist: pyjwt[crypto]>=2.8.0 ; extra == 'auth0'
Requires-Dist: httpx>=0.25.0 ; extra == 'auth0'
Requires-Dist: cyclonedx-python-lib>=7.0.0,<12.0 ; extra == 'sbom'
Requires-Dist: packageurl-python>=0.15.0 ; extra == 'sbom'
Requires-Dist: boto3>=1.34.0 ; extra == 'aws'
Requires-Dist: httpx>=0.27.0 ; extra == 'kms-vault'
Requires-Dist: aioboto3>=12.0.0 ; extra == 'kms-aws'
Requires-Dist: google-cloud-kms>=2.21.0 ; extra == 'kms-gcp'
Requires-Dist: cryptography>=42.0.0 ; extra == 'kms'
Requires-Dist: cryptography>=42.0.0 ; extra == 'kms-all'
Requires-Dist: httpx>=0.27.0 ; extra == 'kms-all'
Requires-Dist: aioboto3>=12.0.0 ; extra == 'kms-all'
Requires-Dist: google-cloud-kms>=2.21.0 ; extra == 'kms-all'
Requires-Dist: mkdocs>=1.6.1 ; extra == 'docs'
Requires-Dist: mkdocs-material>=9.6.22 ; extra == 'docs'
Requires-Dist: mkdocs-redirects>=1.2.2 ; extra == 'docs'
Requires-Dist: pymdown-extensions>=10.16.1 ; extra == 'docs'
Requires-Dist: protobuf>=4.25.8,<7.0 ; extra == 'tracing'
Requires-Dist: wrapt>=1.16.0 ; extra == 'tracing'
Requires-Dist: opentelemetry-api>=1.20.0 ; extra == 'tracing'
Requires-Dist: opentelemetry-sdk>=1.20.0 ; extra == 'tracing'
Requires-Dist: opentelemetry-instrumentation-psycopg>=0.40b0 ; extra == 'tracing'
Requires-Dist: opentelemetry-exporter-otlp>=1.20.0 ; extra == 'tracing'
Requires-Dist: opentelemetry-exporter-jaeger>=1.20.0 ; extra == 'tracing'
Requires-Dist: protobuf>=4.25.8,<7.0 ; extra == 'all'
Requires-Dist: wrapt>=1.16.0 ; extra == 'all'
Requires-Dist: opentelemetry-api>=1.20.0 ; extra == 'all'
Requires-Dist: opentelemetry-sdk>=1.20.0 ; extra == 'all'
Requires-Dist: opentelemetry-instrumentation-psycopg>=0.40b0 ; extra == 'all'
Requires-Dist: opentelemetry-exporter-otlp>=1.20.0 ; extra == 'all'
Requires-Dist: opentelemetry-exporter-jaeger>=1.20.0 ; extra == 'all'
Requires-Dist: pyjwt[crypto]>=2.8.0 ; extra == 'all'
Requires-Dist: httpx>=0.25.0 ; extra == 'all'
Requires-Dist: cyclonedx-python-lib>=7.0.0,<12.0 ; extra == 'all'
Requires-Dist: packageurl-python>=0.15.0 ; extra == 'all'
Requires-Dist: boto3>=1.34.0 ; extra == 'all'
Requires-Dist: cryptography>=42.0.0 ; extra == 'all'
Requires-Dist: aioboto3>=12.0.0 ; extra == 'all'
Requires-Dist: google-cloud-kms>=2.21.0 ; extra == 'all'
Provides-Extra: dev
Provides-Extra: auth0
Provides-Extra: sbom
Provides-Extra: aws
Provides-Extra: kms-vault
Provides-Extra: kms-aws
Provides-Extra: kms-gcp
Provides-Extra: kms
Provides-Extra: kms-all
Provides-Extra: docs
Provides-Extra: tracing
Provides-Extra: all
License-File: LICENSE
Summary: GraphQL for the LLM era. Simple. Powerful. Rust-fast. Production-ready GraphQL API framework for PostgreSQL with CQRS, JSONB optimization, and type-safe mutations
Keywords: graphql,postgresql,api,database,jsonb,fastapi,async,orm
Author-email: Lionel Hamayon <lionel.hamayon@evolution-digitale.fr>
License: MIT
Requires-Python: >=3.13, <3.14
Project-URL: Homepage, https://github.com/fraiseql/fraiseql
Project-URL: Documentation, https://fraiseql.dev
Project-URL: Repository, https://github.com/fraiseql/fraiseql
Project-URL: Issues, https://github.com/fraiseql/fraiseql/issues
Project-URL: Changelog, https://github.com/fraiseql/fraiseql/blob/main/CHANGELOG.md
